RuletaEuropea/Apuesta.py
RuletaEuropea/Constantes.py
RuletaEuropea/Numero.py
RuletaEuropea/Ruleta.py
RuletaEuropea/__init__.py
RuletaEuropea-0.1.6.dist-info/METADATA
RuletaEuropea-0.1.6.dist-info/WHEEL
RuletaEuropea-0.1.6.dist-info/top_level.txt
RuletaEuropea-0.1.6.dist-info/RECORD
