Metadata-Version: 2.1
Name: RuletaEuropea
Version: 0.1.6
Summary: Implementacion de la ruleta europea hecha en python
Author: Marcos Porteiro
